nyc_taxi_fare_model/__init__.py
nyc_taxi_fare_model/custom_type.py
nyc_taxi_fare_model/dataset.py
nyc_taxi_fare_model/model.py
nyc_taxi_fare_model/preprocessor.py
nyc_taxi_fare_model/trainer.py
nyc_taxi_fare_model-0.1.1.1.dist-info/METADATA
nyc_taxi_fare_model-0.1.1.1.dist-info/WHEEL
nyc_taxi_fare_model-0.1.1.1.dist-info/top_level.txt
nyc_taxi_fare_model-0.1.1.1.dist-info/RECORD
